{
  "indexes": [
    {
      "collectionGroup": "assignments",
      "queryScope": "COLLECTION",
      "fields": [
        {
          "fieldPath": "assignedTo",
          "arrayConfig": "CONTAINS"
        },
        {
          "fieldPath": "isActive",
          "order": "ASCENDING"
        },
        {
          "fieldPath": "dueDate",
          "order": "ASCENDING"
        }
      ]
    },
    {
      "collectionGroup": "assignments",
      "queryScope": "COLLECTION",
      "fields": [
        {
          "fieldPath": "createdBy",
          "order": "ASCENDING"
        },
        {
          "fieldPath": "isActive",
          "order": "ASCENDING"
        },
        {
          "fieldPath": "createdAt",
          "order": "DESCENDING"
        }
      ]
    },
    {
      "collectionGroup": "submissions",
      "queryScope": "COLLECTION",
      "fields": [
        {
          "fieldPath": "studentId",
          "order": "ASCENDING"
        },
        {
          "fieldPath": "submittedAt",
          "order": "DESCENDING"
        }
      ]
    },
    {
      "collectionGroup": "submissions",
      "queryScope": "COLLECTION",
      "fields": [
        {
          "fieldPath": "assignmentId",
          "order": "ASCENDING"
        },
        {
          "fieldPath": "submittedAt",
          "order": "DESCENDING"
        }
      ]
    },
    {
      "collectionGroup": "messages",
      "queryScope": "COLLECTION",
      "fields": [
        {
          "fieldPath": "conversationId",
          "order": "ASCENDING"
        },
        {
          "fieldPath": "isDeleted",
          "order": "ASCENDING"
        },
        {
          "fieldPath": "timestamp",
          "order": "ASCENDING"
        }
      ]
    },
    {
      "collectionGroup": "conversations",
      "queryScope": "COLLECTION",
      "fields": [
        {
          "fieldPath": "participants",
          "arrayConfig": "CONTAINS"
        },
        {
          "fieldPath": "lastMessageAt",
          "order": "DESCENDING"
        }
      ]
    },
    {
      "collectionGroup": "notifications",
      "queryScope": "COLLECTION",
      "fields": [
        {
          "fieldPath": "recipientId",
          "order": "ASCENDING"
        },
        {
          "fieldPath": "createdAt",
          "order": "DESCENDING"
        }
      ]
    },
    {
      "collectionGroup": "notifications",
      "queryScope": "COLLECTION",
      "fields": [
        {
          "fieldPath": "recipientId",
          "order": "ASCENDING"
        },
        {
          "fieldPath": "read",
          "order": "ASCENDING"
        }
      ]
    },
    {
      "collectionGroup": "students",
      "queryScope": "COLLECTION",
      "fields": [
        {
          "fieldPath": "assignedTeacher",
          "order": "ASCENDING"
        },
        {
          "fieldPath": "metadata.isActive",
          "order": "ASCENDING"
        }
      ]
    },
    {
      "collectionGroup": "students",
      "queryScope": "COLLECTION",
      "fields": [
        {
          "fieldPath": "metadata.isActive",
          "order": "ASCENDING"
        },
        {
          "fieldPath": "metadata.createdAt",
          "order": "DESCENDING"
        }
      ]
    }
  ],
  "fieldOverrides": []
}